{
  "schemaVersion": 1,
  "id": "simpletransport",
  "version": "${version}",

  "name": "SimpleTransport",
  "description": "SimpleTransport is a mod that brings very simple conveyer-belts, and other related transport-contraptions.",
  "authors": [
    "John Pattox"
  ],
  "contact": {
    "homepage": "https://www.curseforge.com/minecraft/mc-mods/simpletransport-for-fabric",
    "sources": "https://www.curseforge.com/minecraft/mc-mods/simpletransport-for-fabric"
  },

  "license": "MIT",
  "icon": "assets/simpletransport/conveyor.png",

  "environment": "*",
  "entrypoints": {
    "main": [
      "net.pattox.simpletransport.SimpleTransport"
    ]
  },
  "mixins": [

  ],

  "depends": {
    "fabricloader": ">=0.11.3",
    "fabric": "*",
    "minecraft": "1.17.x",
    "java": ">=16"
  },
  "suggests": {
    "another-mod": "*"
  }
}
